setup.py
pathclustering/__init__.py
pathclustering/coordination.py
pathclustering/distance_functions.py
pathclustering/generator_initializer.py
pathclustering/generic_dbscan.py
pathclustering/line_segment_averaging.py
pathclustering/linked_list.py
pathclustering/representative_line_finding.py
pathclustering/representative_trajectory_average_inputs.py
pathclustering/trajectory.py
pathclustering.egg-info/PKG-INFO
pathclustering.egg-info/SOURCES.txt
pathclustering.egg-info/dependency_links.txt
pathclustering.egg-info/not-zip-safe
pathclustering.egg-info/requires.txt
pathclustering.egg-info/top_level.txt