Metadata-Version: 1.0
Name: pathclustering
Version: 0.1
Summary: First pass implementation of traclus algorithm
Home-page: http://github.com/apolcyn/traclus_impl.git
Author: AP
Author-email: alexpolcyn65@gmail.com
License: MIT
Platform: UNKNOWN
